{
    "header": {
        "header_constructor": "KONFIGURATOR",
        "header_catalog": "KATALOG",
        "header_about": "O MNIE",
        "header_review": "OPINIE",
        "header_buy_button": "KUP ZEGAREK"
    },
    "main_page": {
        "first_gallery_watch_name": {
            "slide_1": "Zegarek nr 1",
            "slide_2": "Zegarek nr 3",
            "slide_3": "Zegarek nr 3",
            "first_gallery_watch_button": "zobacz"
        }
    },
    "index": {
        "first_block": {
            "hero-title": "Jaki będzie Twój następny zegarek?",
            "hero-subtitle": "Zanurz się w świat personalizacji i unikalnego designu.",
            "hero-buttons-1": "Konfigurator",
            "hero-buttons-2": "MODELE"
        },
        "concept-block": {
            "h2": "Od pomysłu do realizacji",
            "p1": "Nasze zaangażowanie w jakość widać w każdym zegarku, który tworzymy.",
            "p2": "Każdy element jest starannie dobierany przez Ciebie i dla Ciebie, aby spełnić najwyższe oczekiwania.",
            "p3": "Od wyboru tarczy po dobór bransolety – każdy model to dzieło precyzji i elegancji.",
            "button-1": "Stwórz swój koncept",
            "button-2": "Zobacz gotowe MODELE"
        },
        "how-it-works": {
            "h2": "JAK TO DZIAŁA?",
            "p1": "Wybierz design",
            "p2": "Uzgodnij zamówienie",
            "p3": "Wpłać zaliczkę",
            "p4": "Produkcja zegarka (2–3 tygodnie)",
            "p5": "Zatwierdzenie efektu i dopłata reszty",
            "p6": "Wysyłka zegarka do Ciebie"
        },
        "carousel-tabs": {
            "tab-1": "dostępne do projektowania",
            "tab-2": "gotowe modele"
        },
        "carousel-cards-buttons": {
            "constructor": "Konfigurator",
            "models": "MODELE"
        },
        "carousel-buttons": {
            "button-1": "Stwórz swój koncept",
            "button-2": "Zobacz gotowe MODELE"
        },
        "delivery": {
            "p1": "Czas realizacji – 2-3 tygodnie",
            "p2": "Dostawa do Twojego miasta",
            "p3": "Terminy są ustalane podczas składania zamówienia*"
        },
        "review": {
            "review-title": "OPINIE NASZYCH KLIENTÓW",
            "card-1": "„Odebrałem zegarek – wow! Prawdziwe dzieło sztuki!”",
            "card-2": "„Jestem bardzo zadowolona z jakości! Zegarek wygląda luksusowo i elegancko!”",
            "card-3": "„To najlepszy prezent, jaki sobie zrobiłem! Dziękuję!”",
            "card-4": "„Niesamowite! Zegarek wygląda jeszcze lepiej niż na zdjęciach!”"
        },
        "faq": {
            "q1": "Czy szkło jest szafirowe?",
            "a1": "Tak, stosujemy szkło szafirowe o wysokiej przejrzystości i trwałości.",
            "q2": "Czy można się kąpać w zegarku?",
            "a2": "Tak, jeśli wodoodporność wynosi 100 m lub więcej.",
            "q3": "Czy używasz oryginalnych mechanizmów?",
            "a3": "Tak, używam japońskich mechanizmów Seiko: NH35, NH36, NH34, NH38, NH70.",
            "q4": "test?",
            "a4": "1test"
        }
    },
    "pageConstructorsSections": {
        "title": "KONFIGURATOR",
        "sport": "SPORTOWE/CODZIENNE",
        "classic": "KLASYCZNE"
    },
    "pageConstructorsSport": {
        "BackButton": "wróć",
        "titleSport": "SPORTOWE/CODZIENNE",
        "titleClassic": "KLASYCZNE",
        "unavailable": "Tymczasowo niedostępne"
    },
    "pageConstructorsWatchView": {
        "watchMenu": {
            "bracelet": "Bransoleta",
            "dial": "Tarcza",
            "case": "Koperta",
            "bezel": "Bezel",
            "cristalLinz": "Soczewka cyklop",
            "cyclopHint": "<strong>Soczewka cyklop</strong> to powiększające okienko na szkle zegarka nad datą, zapewniające powiększenie 2,5x. Powoduje, że cyfry daty są większe i łatwiejsze do odczytania",
            "band": "Bransoleta/Pasek",
            "caseAndBracelet": "Koperta i bransoleta",
            "caseAndBezel": "Koperta i bezel",
            "hands": "Wskazówki",
            "secondHand": "Sekundnik",
            "GMTHand": "Wskazówka GMT",
            "GMTHint": "Dodając tę wskazówkę, otrzymasz funkcję GMT, a zegarek będzie wyświetlał czas w drugiej strefie czasowej",
            "additionalOptions": "Opcje dodatkowe",
            "watchBack": "Dekiel:",
            "watchBackSolid": "Pełny dekiel",
            "watchBackTransparent": "Przezroczysty dekiel",
            "rotor": "Rotor",
            "rotorStandart": "Standardowy rotor",
            "rotorCustom": "Niestandardowy rotor",
            "rotorHint": "Ruchomy element z tyłu zegarka, który nakręca mechanizm podczas ruchu ręki.",
            "rotorNumber": "Wprowadź numer rotora:",
            "rotorAcceptButton": "Zastosuj",
            "rotorNumberError": "Wartość tylko od 1 do 129",
            "ingraveTitle": "Grawer:",
            "noIngrave": "Bez graweru",
            "ingrave": "Grawer (+150PLN)",
            "dialLogoTitle": "Logo na tarczy:",
            "noLogo": "Bez logo",
            "sLogo": "Logo \"SEIKO\"",
            "otherLogo": "Własne logo (+50PLN)"
        },
        "watchInfo": {
            "title": "Specyfikacja",
            "movement": "<strong>Mechanizm:</strong> Seiko NH35",
            "movementNH35_NH70": "<strong>Mechanizm:</strong> Seiko NH35/NH70",
            "movementNH34_NH35_NH36": "<strong>Mechanizm:</strong> Seiko NH34/NH35/NH36",
            "movementNH35_NH70_NH71_NH72": "<strong>Mechanizm:</strong> Seiko NH35/NH70/NH71/NH72",
            "movementVK63": "<strong>Mechanizm:</strong> Seiko VK63 (kwarcowy)",
            "cristal": "<strong>Szkło:</strong> Szafirowe",
            "cristalMin": "<strong>Szkło:</strong> Mineralne",
            "caseSize39": "<strong>Średnica koperty:</strong> 39 mm",
            "caseSize397": "<strong>Średnica koperty:</strong> 39.7 mm",
            "caseSize40": "<strong>Średnica koperty:</strong> 40 mm",
            "caseSize41": "<strong>Średnica koperty:</strong> 41 mm",
            "caseSize42": "<strong>Średnica koperty:</strong> 42 mm",
            "caseThickness13": "<strong>Grubość koperty:</strong> 13 mm",
            "caseThickness13_6": "<strong>Grubość koperty:</strong> 13.6 mm",
            "caseThickness15": "<strong>Grubość koperty:</strong> 15 mm",
            "caseMaterial": "<strong>Materiał koperty:</strong> Stal nierdzewna 316L",
            "waterProfile100": "<strong>Wodoszczelność:</strong> 100 m",
            "waterProfile50": "<strong>Wodoszczelność:</strong> 50 m",
            "watchBackSolid": "pełny",
            "watchBackTransparent": "przezroczysty"
        },
        "price": "Cena:",
        "imageDownloadButton": "Pobierz obraz",
        "buyNote": "Możesz również zmienić lub usunąć logo SEIKO oraz dodać grawer. <br> <br> Aby złożyć zamówienie, kliknij przycisk „Pobierz” i wyślij mi to zdjęcie przez komunikator.",
        "whatsAppButton": "Napisz na WhatsApp",
        "viberButton": "Napisz na Viber"
    },
    "footer": {
        "footer_question_1": "Masz pytania?",
        "footer_question_2": "Chętnie odpowiem",
        "footer_terms": "regulamin",
        "footer_privacy": "Polityka prywatności",
        "footer_cookie": "Polityka cookies",
        "footer_cookie_settings": "ustawienia cookies",
        "footer_copyright": "© SURF WATCH. Wszelkie prawa zastrzeżone.",
        "footer_FeedbackButton": "NAPISZ",
        "footer_vat": "VAT no. IT10115350158"
    }
}